textract2page/__init__.py
textract2page/_version.py
textract2page/cli.py
textract2page/convert_aws.py
textract2page-0.3.1.dist-info/LICENSE
textract2page-0.3.1.dist-info/METADATA
textract2page-0.3.1.dist-info/NOTICE
textract2page-0.3.1.dist-info/WHEEL
textract2page-0.3.1.dist-info/entry_points.txt
textract2page-0.3.1.dist-info/top_level.txt
textract2page-0.3.1.dist-info/RECORD
