Metadata-Version: 2.1
Name: textract2page
Version: 0.3.1
Summary: Convert AWS Textract JSON to PRImA PAGE XML
Author: Arne Rümmler
Author-email: arne.ruemmler@gmail.com
License: Apache Software License
Project-URL: homepage, https://github.com/slub/textract2page
Keywords: OCR,METS,PAGE-XML,AWS
Classifier: Programming Language :: Python :: 3
Classifier: Operating System :: OS Independent
Classifier: License :: OSI Approved :: Apache Software License
Classifier: Development Status :: 3 - Alpha
Classifier: Environment :: Console
Classifier: Intended Audience :: Developers
Classifier: Intended Audience :: Education
Classifier: Intended Audience :: Science/Research
Classifier: Topic :: File Formats
Classifier: Topic :: Software Development :: Libraries :: Python Modules
Requires-Python: >=3.7
License-File: LICENSE
License-File: NOTICE
Requires-Dist: click
Requires-Dist: pillow
Requires-Dist: ocrd
